[
    {
        "S.NO": 1,
        "DIRECTORS NAMES": "AJITH KUMAR S",
        "DIN NUMBER": 9855102,
        "EMAIL ID": "djm.ajithkumar@gmail.com",
        "IDBI ACCOUNT DETAILS": "Account Number:\n1319104000172172\nCustomer ID:\n90037818",
        "EMUDRA ACCOUNT DETAILS": "A/c Number\n1993104000042264\nBank Name:\nIDBI Bank\nIFSC CODE Number:\nIBKL0001993\nPlace of Bank (BRANCH):\nBODINAYAKANUR",
        "Aadhar Address": "38(2),Jameen Thoppu Road, \nBodinayakknur, \nTheni - 625513,\nTamilnadu.",
        "Residential Address": "38(2),Jameen Thoppu Road, \nBodinayakknur, \nTheni - 625513,\nTamilnadu.",
        "AADHAR NUMBER": "5565 6631 0349",
        "PAN NUMBER": "BMNPA7370M",
        "Bank link Phone number": "9688538884",
        "Aadhar Pan link Phone number": "6379089025",
        "Email ID Phone number": "6379089025"
    },
    {
        "S.NO": 2,
        "DIRECTORS NAMES": "AMUTHA S",
        "DIN NUMBER": 10577350,
        "EMAIL ID": "djm.amutha@gmail.com",
        "IDBI ACCOUNT DETAILS": "Account Number:\n1993104000047588\nCustomer ID:\n91393912",
        "EMUDRA ACCOUNT DETAILS": "Other Bank A/C Number:\n10073171137\nBank Name:\nTAMILNADU GRAMA BANK\nIFSC CODE Number:\nIDIB0PLB001\nPlace of Bank (BRANCH):\nBODINAYAKKANUR",
        "Aadhar Address": "38(2),Jameen Thoppu Road, \nBodinayakknur, \nTheni - 625513,\nTamilnadu.",
        "Residential Address": "38(2),Jameen Thoppu Road, \nBodinayakknur, \nTheni - 625513,\nTamilnadu.",
        "AADHAR NUMBER": "4462 3032 9539",
        "PAN NUMBER": "EUVPA8967H",
        "Bank link Phone number": "8508369090",
        "Aadhar Pan link Phone number": "9976624924",
        "Email ID Phone number": "8508369090"
    },
    {
        "S.NO": 3,
        "DIRECTORS NAMES": "ASHOK KUMAR N",
        "DIN NUMBER": 9830305,
        "EMAIL ID": "djm.ashokkumar@gmail.com",
        "IDBI ACCOUNT DETAILS": "Account Number:\n1319104000171847\nCustomer ID:\n101399977",
        "EMUDRA ACCOUNT DETAILS": "A/c Number\n1656155000110726\nBank Name:\nKARUR VYSYA BANK\nIFSC CODE Number:\nKVBL0001656\nPlace of Bank (BRANCH):\nPARAMAKUDI",
        "Aadhar Address": "Ashokkumar N\nS/O-Nagarajan M\n8/190Kannagi Street\nParamakudi\nRamanathapuram Dist\nTamilnadu\n623707",
        "Residential Address": "Ashokkumar N\nS/O-Nagarajan M\n8/190Kannagi Street\nParamakudi\nRamanathapuram Dist\nTamilnadu\n623707",
        "AADHAR NUMBER": "4371 6237 5060",
        "PAN NUMBER": "EWRPA9255E",
        "Bank link Phone number": "9524046001",
        "Aadhar Pan link Phone number": "9524046001",
        "Email ID Phone number": "9524046001"
    },
    {
        "S.NO": 4,
        "DIRECTORS NAMES": "BALAJI R",
        "DIN NUMBER": "proposal",
        "EMAIL ID": "djm.balaji@gmail.com",
        "IDBI ACCOUNT DETAILS": "Account Number:\n1319104000180177\nCustomer ID:\n103114854",
        "EMUDRA ACCOUNT DETAILS": "A/c Number\n1008131002331\nBank Name:\nCANARA BANK\nIFSC CODE Number:\nCNRB0001008\nPlace of Bank (BRANCH):\nMADURAI GRAND CENTRAL",
        "Aadhar Address": "3/187\nMuslim Street Keelavalavu\nKeelavalavu (Po)\nMelur (Tk)\nMadurai - 625102.\nTamilnadu.",
        "Residential Address": "S/O Raja\n3/167,Chettiyar Theru\nMuththarasan Textiles Road\nKeelavalavu\nMelur(Tk)\nMadurai - 625102.\nTamilnadu.",
        "AADHAR NUMBER": "6353 3060 6765",
        "PAN NUMBER": "CJQPB8046L",
        "Bank link Phone number": "9524284988",
        "Aadhar Pan link Phone number": "9524284988",
        "Email ID Phone number": "9524284988"
    },
    {
        "S.NO": 5,
        "DIRECTORS NAMES": "BALAMURUGAN A",
        "DIN NUMBER": 8118145,
        "EMAIL ID": "djm.balamurugan@gmail.com",
        "IDBI ACCOUNT DETAILS": "Account Number:\n1319104000171601\nCustomer ID:\n101395738",
        "EMUDRA ACCOUNT DETAILS": "A/c Number\n825210110005105\nBank Name:\nBANK OF INDIA\nIFSC CODE Number:\nBKID0008252\nPlace of Bank (BRANCH):\nTIRUNAGAR, MADURAI",
        "Aadhar Address": "Plot Number 28, Sowbackiya Nagar Second Street,\nTirunagar,\nPo: Tirunagar,\nMadurai, Tamil Nadu-625006.",
        "Residential Address": "Plot Number 28, Sowbackiya Nagar Second Street,\nTirunagar,\nPo: Tirunagar,\nMadurai, Tamil Nadu-625006.",
        "AADHAR NUMBER": "8998 4134 9428",
        "PAN NUMBER": "ABZPB8215G",
        "Bank link Phone number": "9994041624",
        "Aadhar Pan link Phone number": "9994041624",
        "Email ID Phone number": "9994041624"
    },
    {
        "S.NO": 6,
        "DIRECTORS NAMES": "BUVANESWARI C N",
        "DIN NUMBER": 10264257,
        "EMAIL ID": "djm.buvaneswari@gmail.com",
        "IDBI ACCOUNT DETAILS": "Account Number:\n1319104000171816\nCustomer ID:\n101399281",
        "EMUDRA ACCOUNT DETAILS": "A/c Number\n20190376510\nBank Name:\nSTATE BANK OF INDIA\nIFSC CODE Number:\nSBIN0000253\nPlace of Bank (BRANCH):\nTALLAKULAM, MADURAI",
        "Aadhar Address": "Plot No.3, Mms Colony 10Th Cross Street, Kannanenthal,\nMadurai - 625 014,\nTamil Nadu.",
        "Residential Address": "Plot No.3, Mms Colony 10Th Cross Street, Kannanenthal,\nMadurai - 625 014,\nTamil Nadu.",
        "AADHAR NUMBER": "2700 4791 6104",
        "PAN NUMBER": "CLNPB9395P",
        "Bank link Phone number": "8667047636",
        "Aadhar Pan link Phone number": "8838918220",
        "Email ID Phone number": "8667047636"
    },
    {
        "S.NO": 7,
        "DIRECTORS NAMES": "DINESH BABU M",
        "DIN NUMBER": 10561676,
        "EMAIL ID": "djm.dineshbabu@gmail.com",
        "IDBI ACCOUNT DETAILS": "Account Number:\n1319104000171670\nCustomer ID:\n101396476",
        "EMUDRA ACCOUNT DETAILS": "A/c Number\n36930630596\nBank Name:\nSTATE BANK OF INDIA\nIFSC CODE Number:\nSBIN0002247\nPlace of Bank (BRANCH):\nPALAMEDU",
        "Aadhar Address": "S/O:Manikaalai,\n1/10,1St Street Senthamangalam\nMadurai - 625503.\nTamil Nadu.",
        "Residential Address": "1/361 Edwin Nagar Society Backside\nPalamedu\nVadipatti(Tk)\nMadurai(Dt) 625503",
        "AADHAR NUMBER": "6118 0433 8971",
        "PAN NUMBER": "HHXPD5257B",
        "Bank link Phone number": "9384123086",
        "Aadhar Pan link Phone number": "9384123086",
        "Email ID Phone number": "9384123086"
    },
    {
        "S.NO": 8,
        "DIRECTORS NAMES": "ELANGOVAN N",
        "DIN NUMBER": 6732396,
        "EMAIL ID": "djm.elangovan@gmail.com",
        "IDBI ACCOUNT DETAILS": "Account Number:\n1319104000175982\nCustomer ID:\n102173500",
        "EMUDRA ACCOUNT DETAILS": "A/c Number\n10241951989\nBank Name:\nSTATE BANK OF INDIA\nIFSC CODE Number:\nSBIN0061767\nPlace of Bank (BRANCH):\nTIRUVANCHERRY",
        "Aadhar Address": "No.8, Secretariat Colony,\nAgaram Then Main Road,\nPaduvanchery,\nMadambakkam, Tambaram.\nChennai- 600126.",
        "Residential Address": "No.8, Secretariat Colony,\nAgaram Then Main Road,\nPaduvanchery,\nMadambakkam, Tambaram.\nChennai- 600126.",
        "AADHAR NUMBER": "7007 3491 4209",
        "PAN NUMBER": "ATRPN3022D",
        "Bank link Phone number": "9176909841",
        "Aadhar Pan link Phone number": "9176909841",
        "Email ID Phone number": "9176909841"
    },
    {
        "S.NO": 9,
        "DIRECTORS NAMES": "GNANASEKARAN A",
        "DIN NUMBER": 10225471,
        "EMAIL ID": "djm.gnanasekaran@gmail.com",
        "IDBI ACCOUNT DETAILS": "Account Number:\n1319104000172110\nCustomer ID:\n85103436",
        "EMUDRA ACCOUNT DETAILS": "A/c Number\nNIL\nBank Name:\nNIL\nIFSC CODE Number:\nNIL\nPlace of Bank (BRANCH):\nNIL",
        "Aadhar Address": "No7/29, Thiruvalluvar Lane,\nSundrapandianstreet,\nBodinayakkanur,\nTheni - 625513,\nTamil Nadu.",
        "Residential Address": "No7/29, Thiruvalluvar Lane,\nSundrapandianstreet,\nBodinayakkanur,\nTheni - 625513,\nTamil Nadu.",
        "AADHAR NUMBER": "2941 4103 2772",
        "PAN NUMBER": "BFBPG6217C",
        "Bank link Phone number": "9043586691",
        "Aadhar Pan link Phone number": "9894736691",
        "Email ID Phone number": "9894736691"
    },
    {
        "S.NO": 10,
        "DIRECTORS NAMES": "GUNASEKARI P",
        "DIN NUMBER": 10225472,
        "EMAIL ID": "djm.gunasekari@gmail.com",
        "IDBI ACCOUNT DETAILS": "Account Number:\n1319104000171694\nCustomer ID:\n101396477",
        "EMUDRA ACCOUNT DETAILS": "A/c Number\n41229041691\nBank Name:\nSTATE BANK OF INDIA\nIFSC CODE Number:\nSBIN0000787\nPlace of Bank (BRANCH):\nTIRUPATTUR",
        "Aadhar Address": "33, Sunnambiruppu\nKottaiyiruppu Post\nThiruppathur Taluk\nSivagangai District -630211",
        "Residential Address": "33, Sunnambiruppu\nKottaiyiruppu Post\nThiruppathur Taluk\nSivagangai District -630211",
        "AADHAR NUMBER": "7633 5176 8651",
        "PAN NUMBER": "HBFPP0423P",
        "Bank link Phone number": "6384204230",
        "Aadhar Pan link Phone number": "6384204230",
        "Email ID Phone number": "6384204230"
    },
    {
        "S.NO": 11,
        "DIRECTORS NAMES": "HARIHARAN T N",
        "DIN NUMBER": 10249130,
        "EMAIL ID": "djm.hariharan@gmail.com",
        "IDBI ACCOUNT DETAILS": "Account Number:\n1319104000171625\nCustomer ID:\n101395796",
        "EMUDRA ACCOUNT DETAILS": "A/c Number\n327100050306492\nBank Name:\nTAMILNAD MERCHANTILE BANK\nIFSC CODE Number:\nTMBL0000327\nPlace of Bank (BRANCH):\nVILLAPURAM",
        "Aadhar Address": "#22, Krishna Street,\nMeenatchi Nagar,\nVillapuram,\nMadurai - 625012.",
        "Residential Address": "#22, Krishna Street,\nMeenatchi Nagar,\nVillapuram,\nMadurai - 625012.",
        "AADHAR NUMBER": "6049 7590 9371",
        "PAN NUMBER": "AFTPH7129F",
        "Bank link Phone number": "8428488044",
        "Aadhar Pan link Phone number": "8825588044",
        "Email ID Phone number": "8428488044"
    },
    {
        "S.NO": 12,
        "DIRECTORS NAMES": "JAYANTH R",
        "DIN NUMBER": 10564393,
        "EMAIL ID": "djm.jayanth@gmail.com",
        "IDBI ACCOUNT DETAILS": "Account Number:\n0006104000627887\nCustomer ID:\n102526009",
        "EMUDRA ACCOUNT DETAILS": "A/c Number\nNIL\nBank Name:\nNIL\nIFSC CODE Number:\nNIL\nPlace of Bank (BRANCH):\nNIL",
        "Aadhar Address": "5/A 11,\nAsokar Street,\nSri Nagar,\nCoimbatore South,\nCoimbatore -641111.\nTamilnadu.",
        "Residential Address": "No 10/3, 2Nd Floor,\nChennai Realtors Apartment,\n60Ft Road, Tnhb Colony,\nSinganallur, Coimbatore.\nTamilnadu - 641005.",
        "AADHAR NUMBER": "8674 1223 0342",
        "PAN NUMBER": "CNNPJ4184J",
        "Bank link Phone number": "8825803694",
        "Aadhar Pan link Phone number": "9488449198",
        "Email ID Phone number": "8825803694"
    },
    {
        "S.NO": 13,
        "DIRECTORS NAMES": "KALPANA DEVI N",
        "DIN NUMBER": 10566501,
        "EMAIL ID": "djm.kalpanadevi@gmail.com",
        "IDBI ACCOUNT DETAILS": "Account Number:\n1319104000175913\nCustomer ID:\n102173489",
        "EMUDRA ACCOUNT DETAILS": "A/c Number\n10169744262\nBank Name:\nSTATE BANK OF INDIA\nIFSC CODE Number:\nSBIN0007482\nPlace of Bank (BRANCH):\nARASARADI",
        "Aadhar Address": "11-1-1, Mariamman Kovil Middle Street,\nSholavandan,\nMadurai - 625214.",
        "Residential Address": "11-1-1, Mariamman Kovil Middle Street,\nSholavandan,\nMadurai - 625214.",
        "AADHAR NUMBER": "7211 2733 6655",
        "PAN NUMBER": "FEDPK3794F",
        "Bank link Phone number": "9345144201",
        "Aadhar Pan link Phone number": "9345144201",
        "Email ID Phone number": "9345144201"
    },
    {
        "S.NO": 14,
        "DIRECTORS NAMES": "KALPANA KARTHICK N B",
        "DIN NUMBER": 10565811,
        "EMAIL ID": "djm.kalpana@gmail.com",
        "IDBI ACCOUNT DETAILS": "Account Number:\n1319104000175968\nCustomer ID:\n102173496",
        "EMUDRA ACCOUNT DETAILS": "A/c Number\n002100050314219\nBank Name:\nTAMILNAD MERCHANTILE BANK\nIFSC CODE Number:\nTMBL0000002\nPlace of Bank (BRANCH):\nMADURAI MAIN",
        "Aadhar Address": "20A, Kamarajar 2Nd Street,\nManikandan Nagar,\nVillapuram,\nMadurai - 625 012.\nTamil Nadu.",
        "Residential Address": "20A, Kamarajar 2Nd Street,\nManikandan Nagar,\nVillapuram,\nMadurai - 625 012.\nTamil Nadu.",
        "AADHAR NUMBER": "3936 4979 2482",
        "PAN NUMBER": "EINPK9064D",
        "Bank link Phone number": "9843211719",
        "Aadhar Pan link Phone number": "9843211719",
        "Email ID Phone number": "9843211719"
    },
    {
        "S.NO": 15,
        "DIRECTORS NAMES": "KALYANI B",
        "DIN NUMBER": 10554211,
        "EMAIL ID": "djm.kalyanibalamurugan@gmail.com",
        "IDBI ACCOUNT DETAILS": "Account Number:\n1319104000175951\nCustomer ID:\n102173495",
        "EMUDRA ACCOUNT DETAILS": "A/c Number\n6837577620\nBank Name:\nINDIAN BANK\nIFSC CODE Number:\nIDIB000T032\nPlace of Bank (BRANCH):\nTIRUNAGAR, MADURAI",
        "Aadhar Address": "Plot Number 28, Sowbackiya Nagar Second Street,\nTirunagar,\nPo: Tirunagar,\nMadurai, Tamil Nadu-625006.",
        "Residential Address": "Plot Number 28, Sowbackiya Nagar Second Street,\nTirunagar,\nPo: Tirunagar,\nMadurai, Tamil Nadu-625006.",
        "AADHAR NUMBER": "7007 6872 2142",
        "PAN NUMBER": "AJHPK8771E",
        "Bank link Phone number": "9790127281",
        "Aadhar Pan link Phone number": "9790127281",
        "Email ID Phone number": "9790127281"
    },
    {
        "S.NO": 16,
        "DIRECTORS NAMES": "KALYANI R",
        "DIN NUMBER": 10565747,
        "EMAIL ID": "djm.kalyani@gmail.com",
        "IDBI ACCOUNT DETAILS": "Account Number:\n1319104000171892\nCustomer ID:\n101400278",
        "EMUDRA ACCOUNT DETAILS": "A/c Number\n1656155000112176\nBank Name:\nKARUR VYSYA BANK\nIFSC CODE Number:\nKVBL0001656\nPlace of Bank (BRANCH):\nPARAMAKUDI",
        "Aadhar Address": "8/200-2 Kannaki Street\nParamakudi 623707.",
        "Residential Address": "8/200-2 Kannaki Street\nParamakudi 623707.",
        "AADHAR NUMBER": "9046 0934 4217",
        "PAN NUMBER": "DZOPK3749A",
        "Bank link Phone number": "9524833546",
        "Aadhar Pan link Phone number": "9524833546",
        "Email ID Phone number": "9524833546"
    },
    {
        "S.NO": 17,
        "DIRECTORS NAMES": "KIRUTHIKA V",
        "DIN NUMBER": 10577903,
        "EMAIL ID": "djm.kiruthika@gmail.com",
        "IDBI ACCOUNT DETAILS": "Account Number:\n1319104000171885\nCustomer ID:\n101400193",
        "EMUDRA ACCOUNT DETAILS": "A/c Number\n110117705558\nBank Name:\nCANARA BANK\nIFSC CODE Number:\nCNRB0000919\nPlace of Bank (BRANCH):\nPARAMAKUDI",
        "Aadhar Address": "8/188 A, Kannaki Street\nParamakudi-623707.",
        "Residential Address": "8/188 A, Kannaki Street\nParamakudi-623707.",
        "AADHAR NUMBER": "7246 1053 9031",
        "PAN NUMBER": "NKMPK0494K",
        "Bank link Phone number": "9003332339",
        "Aadhar Pan link Phone number": "9003332339",
        "Email ID Phone number": "9003332339"
    },
    {
        "S.NO": 18,
        "DIRECTORS NAMES": "LAKSHMIKANTH K R",
        "DIN NUMBER": 9846160,
        "EMAIL ID": "djm.lakshmikanth@gmail.com",
        "IDBI ACCOUNT DETAILS": "Account Number:\n1319104000171540\nCustomer ID:\n101395531",
        "EMUDRA ACCOUNT DETAILS": "A/c Number\n7112120196\nBank Name:\nINDIAN BANK\nIFSC CODE Number:\nIDIB000V020\nPlace of Bank (BRANCH):\nVILAKKUTHOON, MADURAI",
        "Aadhar Address": "No.17, Krishnapuram 4Th Cross Street,\nMunichalai,\nMadurai -625009,\nTamilnadu.",
        "Residential Address": "21, Poonthodam Street,\nKamarajar Salai,\nMadurai - 625009.\nTamilnadu.",
        "AADHAR NUMBER": "5317 9287 0611",
        "PAN NUMBER": "ADHPL8931H",
        "Bank link Phone number": "8015664792",
        "Aadhar Pan link Phone number": "8015664792",
        "Email ID Phone number": "8015664792"
    },
    {
        "S.NO": 19,
        "DIRECTORS NAMES": "MAHADEVAN L",
        "DIN NUMBER": 9794582,
        "EMAIL ID": "djm.mahadevan@gmail.com",
        "IDBI ACCOUNT DETAILS": "Account Number:\n1319104000171458\nCustomer ID:\n101394784",
        "EMUDRA ACCOUNT DETAILS": "A/c Number\n493966254\nBank Name:\nINDIAN BANK\nIFSC CODE Number:\nIDIB000T032\nPlace of Bank (BRANCH):\nTIRUNAGAR, MADURAI",
        "Aadhar Address": "D.28 Veera Raghava Perumal Street,\nTirunagar,\nMadurai - 625006,\nTamil Nadu.",
        "Residential Address": "D.28 Veera Raghava Perumal Street,\nTirunagar,\nMadurai - 625006,\nTamil Nadu.",
        "AADHAR NUMBER": "4298 4374 7181",
        "PAN NUMBER": "BFWPM7558F",
        "Bank link Phone number": "9443774625",
        "Aadhar Pan link Phone number": "9443774625",
        "Email ID Phone number": "9443774625"
    },
    {
        "S.NO": 20,
        "DIRECTORS NAMES": "MAHESH C",
        "DIN NUMBER": 10577367,
        "EMAIL ID": "djm.maheshc@gmail.com",
        "IDBI ACCOUNT DETAILS": "Account Number:\n1993104000096362\nCustomer ID:\n100258337",
        "EMUDRA ACCOUNT DETAILS": "A/c Number\nNIL\nBank Name:\nNIL\nIFSC CODE Number:\nNIL\nPlace of Bank (BRANCH):\nNIL",
        "Aadhar Address": "C-3 Voc Nagar,\nMiddle Street,\nBodinayakanur\nTheni - 625513.\nTamilnadu.",
        "Residential Address": "38(2),Jameen Thoppu Road,\nBodinayakknur,\nTheni - 625513,\nTamil Nadu.",
        "AADHAR NUMBER": "8339 9656 9352",
        "PAN NUMBER": "INVPM4204G",
        "Bank link Phone number": "8682877100",
        "Aadhar Pan link Phone number": "8682877100",
        "Email ID Phone number": "8682877100"
    },
    {
        "S.NO": 21,
        "DIRECTORS NAMES": "MAHESHKUMAR S",
        "DIN NUMBER": 9830304,
        "EMAIL ID": "djm.maheshkumar@gmail.com",
        "IDBI ACCOUNT DETAILS": "Account Number:\n1319104000171878\nCustomer ID:\n101400202",
        "EMUDRA ACCOUNT DETAILS": "A/c Number\n3419101013413\nBank Name:\nCANARA BANK\nIFSC CODE Number:\nCNRB0003419\nPlace of Bank (BRANCH):\nMELUR",
        "Aadhar Address": "3/6, Madurai Trichy Main Road,\nMelur, Madurai, Tamil Nadu - 625106.",
        "Residential Address": "3/6, Madurai Trichy Main Road,\nMelur, Madurai, Tamil Nadu - 625106.",
        "AADHAR NUMBER": "5411 0641 8884",
        "PAN NUMBER": "BZKPM1359J",
        "Bank link Phone number": "8098344876",
        "Aadhar Pan link Phone number": "8098344876",
        "Email ID Phone number": "8098344876"
    },
    {
        "S.NO": 22,
        "DIRECTORS NAMES": "MAHESWARI A",
        "DIN NUMBER": 10282503,
        "EMAIL ID": "djm.maheswari@gmail.com",
        "IDBI ACCOUNT DETAILS": "Account Number:\n1319104000171595\nCustomer ID:\n101395708",
        "EMUDRA ACCOUNT DETAILS": "A/c Number\n254501000000410\nBank Name:\nINDIAN OVERSEAS BANK\nIFSC CODE Number:\nIOBA0002545\nPlace of Bank (BRANCH):\nANNUPPANADI, MADURAI",
        "Aadhar Address": "3/226, Lkt 7Th St.,\nLkt Nagar,\nPuliyankulam(Po),\nSilaiman,\nMadurai - 625201.",
        "Residential Address": "3/226, Lkt 7Th St.,\nLkt Nagar,\nPuliyankulam(Po),\nSilaiman,\nMadurai - 625201.",
        "AADHAR NUMBER": "8471 5651 1512",
        "PAN NUMBER": "AWXPM3500E",
        "Bank link Phone number": "9944566610",
        "Aadhar Pan link Phone number": "9944566610",
        "Email ID Phone number": "9944566610"
    },
    {
        "S.NO": 23,
        "DIRECTORS NAMES": "MALAR JOTHI D",
        "DIN NUMBER": 9855204,
        "EMAIL ID": "djm.malarjothi@gmail.com",
        "IDBI ACCOUNT DETAILS": "Account Number:\n1319104000171793\nCustomer ID:\n101398948",
        "EMUDRA ACCOUNT DETAILS": "A/c Number\n1159155000241684\nBank Name:\nKARUR VYSYA BANK\nIFSC CODE Number:\nKVBL0001159\nPlace of Bank (BRANCH):\nWEST TOWER, MADURAI",
        "Aadhar Address": "5/303,\nV.O.C 2Nd Street,\nThasildar Nagar,\nMadurai -625020\nTamil Nadu.",
        "Residential Address": "5/303,\nV.O.C 2Nd Street,\nThasildar Nagar,\nMadurai -625020\nTamil Nadu.",
        "AADHAR NUMBER": "4975 7568 5771",
        "PAN NUMBER": "EYLPM0217A",
        "Bank link Phone number": "9659402066",
        "Aadhar Pan link Phone number": "9659402066",
        "Email ID Phone number": "9659402066"
    },
    {
        "S.NO": 24,
        "DIRECTORS NAMES": "MANOHARAN P",
        "DIN NUMBER": 7404691,
        "EMAIL ID": "djm.manoharan@gmail.com",
        "IDBI ACCOUNT DETAILS": "Account Number:\n1319104000172165\nCustomer ID:\n82912278",
        "EMUDRA ACCOUNT DETAILS": "A/c Number\n10933463691\nBank Name:\nSTATE BANK OF INDIA\nIFSC CODE Number:\nSBIN0000856\nPlace of Bank (BRANCH):\nKARUR",
        "Aadhar Address": "2/558, Third Cross,\nAmirthambal Nagar,\nAthur - Govindampalayam Road,\nKarur - 639008.",
        "Residential Address": "2/558, Third Cross,\nAmirthambal Nagar,\nAthur - Govindampalayam Road,\nKarur - 639008.",
        "AADHAR NUMBER": "3097 1760 9911",
        "PAN NUMBER": "AIAPM5778R",
        "Bank link Phone number": "9443008689",
        "Aadhar Pan link Phone number": "9443008689",
        "Email ID Phone number": "9443008689"
    },
    {
        "S.NO": 25,
        "DIRECTORS NAMES": "NAGANATHAN S",
        "DIN NUMBER": 10554209,
        "EMAIL ID": "djm.naganathan@gmail.com",
        "IDBI ACCOUNT DETAILS": "Account Number:\n1319104000172141\nCustomer ID:\n73069069",
        "EMUDRA ACCOUNT DETAILS": "A/c Number\n7360830452\nBank Name:\nINDIAN BANK\nIFSC CODE Number:\nIDIB000V020\nPlace of Bank (BRANCH):\nVILAKKUTHOON, MADURAI",
        "Aadhar Address": "22/32, Jawagar Salai,\nTamilan Street,\nNew Ramnath Road,\nMadurai - 625009.",
        "Residential Address": "22/32, Jawagar Salai,\nTamilan Street,\nNew Ramnath Road,\nMadurai - 625009.",
        "AADHAR NUMBER": "6717 5276 0484",
        "PAN NUMBER": "AIVPN2052J",
        "Bank link Phone number": "9361039137",
        "Aadhar Pan link Phone number": "9361039137",
        "Email ID Phone number": "9361039137"
    },
    {
        "S.NO": 26,
        "DIRECTORS NAMES": "NAGARAJAN C S",
        "DIN NUMBER": 10561629,
        "EMAIL ID": "djm.nagarajan@gmail.com",
        "IDBI ACCOUNT DETAILS": "Account Number:\n1319104000171908\nCustomer ID:\n101400398",
        "EMUDRA ACCOUNT DETAILS": "A/c Number\n39204783220\nBank Name:\nSTATE BANK OF INDIA\nIFSC CODE Number:\nSBIN0000253\nPlace of Bank (BRANCH):\nTALLAKULAM, MADURAI",
        "Aadhar Address": "Plot No.3, Mms Colony 10Th Cross Street, Kannanenthal,\nMadurai - 625 014,\nTamil Nadu.",
        "Residential Address": "Plot No.3, Mms Colony 10Th Cross Street, Kannanenthal,\nMadurai - 625 014,\nTamil Nadu.",
        "AADHAR NUMBER": "3751 8052 8252",
        "PAN NUMBER": "AIXPN4478J",
        "Bank link Phone number": "8838918220",
        "Aadhar Pan link Phone number": "8838918220",
        "Email ID Phone number": "8838918220"
    },
    {
        "S.NO": 27,
        "DIRECTORS NAMES": "NAGARANI A",
        "DIN NUMBER": 9855203,
        "EMAIL ID": "djm.nagarani@gmail.com",
        "IDBI ACCOUNT DETAILS": "Account Number:\n1319104000171762\nCustomer ID:\n101398804",
        "EMUDRA ACCOUNT DETAILS": "A/c Number\n1159155000241566\nBank Name:\nKARUR VYSYA BANK\nIFSC CODE Number:\nKVBL0001159\nPlace of Bank (BRANCH):\nWEST TOWER, MADURAI",
        "Aadhar Address": "No 9, Karimsha Pallivasal 5Th Street,\nMadurai - 625001\nTamilnadu.",
        "Residential Address": "No 9, Karimsha Pallivasal 5Th Street,\nMadurai - 625001\nTamilnadu.",
        "AADHAR NUMBER": "3239 6845 6667",
        "PAN NUMBER": "AMMPN6931D",
        "Bank link Phone number": "7845801560",
        "Aadhar Pan link Phone number": "7845801560",
        "Email ID Phone number": "7845801560"
    },
    {
        "S.NO": 28,
        "DIRECTORS NAMES": "NAMASIVAYAM M",
        "DIN NUMBER": 9839529,
        "EMAIL ID": "djm.namasivayam@gmail.com",
        "IDBI ACCOUNT DETAILS": "Account Number:\n1319104000171472\nCustomer ID:\n101395069",
        "EMUDRA ACCOUNT DETAILS": "A/c Number\n36043798977\nBank Name:\nSTATE BANK OF INDIA\nIFSC CODE Number:\nSBIN0002270\nPlace of Bank (BRANCH):\nSHOLAVANDAN",
        "Aadhar Address": "11-1-1, Mariamman Kovil Middle Street,\nSholavandan,\nMadurai - 625214.",
        "Residential Address": "11-1-1, Mariamman Kovil Middle Street,\nSholavandan,\nMadurai - 625214.",
        "AADHAR NUMBER": "2238 5378 1660",
        "PAN NUMBER": "BFEPN5310Q",
        "Bank link Phone number": "9362767038",
        "Aadhar Pan link Phone number": "9362767038",
        "Email ID Phone number": "9362767038"
    },
    {
        "S.NO": 29,
        "DIRECTORS NAMES": "PAULPANDI V",
        "DIN NUMBER": 9830303,
        "EMAIL ID": "djm.paulpandi@gmail.com",
        "IDBI ACCOUNT DETAILS": "Account Number:\n1319104000180214\nCustomer ID:\n101400087",
        "EMUDRA ACCOUNT DETAILS": "A/c Number\n163100050308450\nBank Name:\nTAMILNAD MERCHANTILE BANK\nIFSC CODE Number:\nTMBL0000163\nPlace of Bank (BRANCH):\nTALLAKULAM, MADURAI",
        "Aadhar Address": "467,Kamarajar 2Nd Street,\nB. B. Kulam,\nMadurai -625002.",
        "Residential Address": "466,Kamarajar 2Nd Street,\nB. B. Kulam\nMadurai -625002.",
        "AADHAR NUMBER": "5057 2735 1159",
        "PAN NUMBER": "BWSPP0810J",
        "Bank link Phone number": "9790323750",
        "Aadhar Pan link Phone number": "9790323750",
        "Email ID Phone number": "9790323750"
    },
    {
        "S.NO": 30,
        "DIRECTORS NAMES": "PERIASAMY PR",
        "DIN NUMBER": "Proposal",
        "EMAIL ID": "djm.periasamy@gmail.com",
        "IDBI ACCOUNT DETAILS": "Account Number:\nNIL\nCustomer ID:\nNIL",
        "EMUDRA ACCOUNT DETAILS": "A/c Number\n11173298020\nBank Name:\nSTATE BANK OF INDIA\nIFSC CODE Number:\nSBIN0000787\nPlace of Bank (BRANCH):\nACB TIRUPATTUR, MADURAI",
        "Aadhar Address": "33, Sunnambiruppu\nKottaiyiruppu Post\nThiruppathur Taluk\nSivagangai District -630211",
        "Residential Address": "33, Sunnambiruppu\nKottaiyiruppu Post\nThiruppathur Taluk\nSivagangai District -630211",
        "AADHAR NUMBER": "4322 7933 7684",
        "PAN NUMBER": "AYFPP1221M",
        "Bank link Phone number": "",
        "Aadhar Pan link Phone number": "9444405171",
        "Email ID Phone number": "8760052173"
    }
]